LICENSE
README.md
setup.py
fingerprint_feature_extractor/__init__.py
fingerprint_feature_extractor.egg-info/PKG-INFO
fingerprint_feature_extractor.egg-info/SOURCES.txt
fingerprint_feature_extractor.egg-info/dependency_links.txt
fingerprint_feature_extractor.egg-info/requires.txt
fingerprint_feature_extractor.egg-info/top_level.txt