Metadata-Version: 2.1
Name: fingerprint-feature-extractor
Version: 0.0.8
Summary: extract fingerprint minutiae features
Home-page: https://github.com/Utkarsh-Deshmukh/Fingerprint-Feature-Extraction
Download-URL: https://github.com/Utkarsh-Deshmukh/Fingerprint-Feature-Extraction/archive/master.zip
Author: utkarsh-deshmukh
Author-email: utkarsh.deshmukh@gmail.com
License: MIT
Keywords: Fingerprint Minutiae Feature Extraction
Platform: UNKNOWN
Classifier: Programming Language :: Python :: 3
Classifier: License :: OSI Approved :: MIT License
Classifier: Operating System :: OS Independent
License-File: LICENSE
